search_png/__init__.py
search_png/search_png.py
search_png-0.1.0.dist-info/METADATA
search_png-0.1.0.dist-info/WHEEL
search_png-0.1.0.dist-info/top_level.txt
search_png-0.1.0.dist-info/RECORD
